Python_jp/__init__.py
Python_jp/cli.py
Python_jp/exceptions.py
Python_jp/keywords.py
Python_jp/preprocessor.py
Python_jp/runner.py
Python_jp/translator.py
Python_jp/utils.py
Python_jp-0.1.0.data/scripts/python_jp
Python_jp-0.1.0.dist-info/METADATA
Python_jp-0.1.0.dist-info/WHEEL
Python_jp-0.1.0.dist-info/entry_points.txt
Python_jp-0.1.0.dist-info/top_level.txt
Python_jp-0.1.0.dist-info/RECORD
