Metadata-Version: 2.1
Name: Python-jp
Version: 0.1.0
Summary: Python with Japanese keywords
Home-page: https://github.com/unseen2004/Python_jp
Author: Unseen
Author-email: csgo20041@gmail.com
Classifier: Development Status :: 3 - Alpha
Classifier: Intended Audience :: Developers
Classifier: License :: OSI Approved :: MIT License
Classifier: Programming Language :: Python :: 3
Classifier: Programming Language :: Python :: 3.7
Classifier: Programming Language :: Python :: 3.8
Classifier: Programming Language :: Python :: 3.9
Classifier: Programming Language :: Python :: 3.10
Requires-Python: >=3.7
